DynaTMT/DynaTMT.py
DynaTMT/__init__.py
DynaTMT_py-0.4.0.dist-info/LICENSE
DynaTMT_py-0.4.0.dist-info/METADATA
DynaTMT_py-0.4.0.dist-info/WHEEL
DynaTMT_py-0.4.0.dist-info/top_level.txt
DynaTMT_py-0.4.0.dist-info/RECORD
