Metadata-Version: 2.1
Name: DynaTMT-py
Version: 0.4.0
Summary: Python package to analyse pSILAC TMT data
Home-page: https://github.com/bobbyhaze/DynaTMT-py
Author: Kevin Klann
Author-email: klann@em.uni-frankfurt.de
License: UNKNOWN
Platform: UNKNOWN
Classifier: Programming Language :: Python :: 3.8
Classifier: License :: OSI Approved :: MIT License
Classifier: Operating System :: OS Independent
Requires-Python: >=3.6
License-File: LICENSE
